Metadata-Version: 1.1
Name: django-sendgrid-webhook
Version: 0.2.2
Summary: A small django app around sendgrid and its webhooks
Home-page: https://github.com/resmio/django-sendgrid
Author: Jann Kleen
Author-email: jann.kleen@gmail.com
License: BSD 2-Clause
Platform: UNKNOWN
Classifier: Topic :: Internet :: WWW/HTTP :: Dynamic Content
Classifier: Intended Audience :: Developers
Classifier: Programming Language :: Python
Classifier: Programming Language :: Python :: 2.7
Classifier: Framework :: Django
Classifier: Development Status :: 4 - Beta
Classifier: Operating System :: OS Independent
